Audit/__init__.py
Audit/common/AppConfigurations.py
Audit/common/AppConstants.py
Audit/common/__init__.py
Audit/core/__init__.py
Audit/core/applications/Annotations.py
Audit/core/applications/AuditManagement.py
Audit/core/applications/AuditManagementModules.py
Audit/core/applications/AuditUserManagementStrategies.py
Audit/core/applications/__init__.py
Audit/core/persistences/PersistenceAdaptor.py
Audit/core/persistences/__init__.py
Audit/core/persistences/adaptors/CassandraPersistenceAdaptor.py
Audit/core/persistences/adaptors/__init__.py
Audit/core/services/__init__.py
Audit/core/services/audit_service.py
Audit/util/CommonUtils.py
Audit/util/LoggerUtil.py
Audit/util/Logging.py
Audit/util/__init__.py
conf/__init__.py
logs/__init__.py
upload/__init__.py
upload/__root__.py
setup_services-0.1.dist-info/METADATA
setup_services-0.1.dist-info/WHEEL
setup_services-0.1.dist-info/top_level.txt
setup_services-0.1.dist-info/RECORD
