Metadata-Version: 2.1
Name: setup-services
Version: 0.1
Summary: A Docker and AWS utility package
Home-page: https://github.com/javatechy/dokr
Author: Deepak Kumar
Author-email: deepak.kumar.iet@gmail.com
License: UNKNOWN
Platform: UNKNOWN
Classifier: Programming Language :: Python :: 3
Classifier: License :: OSI Approved :: MIT License
Classifier: Operating System :: OS Independent
